{
  "db_name": "SQLite",
  "query": "SELECT contract_id as \"contract_id!\", instance_ip, instance_credentials, connection_instructions, provisioned_at_ns as \"provisioned_at_ns!\" FROM contract_provisioning_details WHERE contract_id = ?",
  "describe": {
    "columns": [
      {
        "name": "contract_id!",
        "ordinal": 0,
        "type_info": "Blob"
      },
      {
        "name": "instance_ip",
        "ordinal": 1,
        "type_info": "Text"
      },
      {
        "name": "instance_credentials",
        "ordinal": 2,
        "type_info": "Text"
      },
      {
        "name": "connection_instructions",
        "ordinal": 3,
        "type_info": "Text"
      },
      {
        "name": "provisioned_at_ns!",
        "ordinal": 4,
        "type_info": "Integer"
      }
    ],
    "parameters": {
      "Right": 1
    },
    "nullable": [
      true,
      true,
      true,
      true,
      false
    ]
  },
  "hash": "f87d42b1992823f1f4e8e7377c287a5b1450e24124baba28cee1175dc9303d7c"
}
