{
  "db_name": "PostgreSQL",
  "query": "\n            SELECT\n                COUNT(*) as \"total!: i64\",\n                COALESCE(SUM(CASE WHEN response_time <= $1 THEN 1 ELSE 0 END), 0) as \"within_1h!: i64\",\n                COALESCE(SUM(CASE WHEN response_time <= $2 THEN 1 ELSE 0 END), 0) as \"within_4h!: i64\",\n                COALESCE(SUM(CASE WHEN response_time <= $3 THEN 1 ELSE 0 END), 0) as \"within_12h!: i64\",\n                COALESCE(SUM(CASE WHEN response_time <= $4 THEN 1 ELSE 0 END), 0) as \"within_24h!: i64\",\n                COALESCE(SUM(CASE WHEN response_time <= $5 THEN 1 ELSE 0 END), 0) as \"within_72h!: i64\"\n            FROM (\n                SELECT\n                    MIN(response.created_at - customer_msg.created_at) as response_time\n                FROM chatwoot_message_events customer_msg\n                JOIN contract_sign_requests c ON encode(c.contract_id, 'hex') = customer_msg.contract_id\n                JOIN chatwoot_message_events response ON\n                    response.chatwoot_conversation_id = customer_msg.chatwoot_conversation_id\n                    AND response.sender_type = 'provider'\n                    AND response.created_at > customer_msg.created_at\n                WHERE customer_msg.sender_type = 'customer'\n                    AND c.provider_pubkey = $6\n                GROUP BY customer_msg.id\n            )\n            ",
  "describe": {
    "columns": [
      {
        "ordinal": 0,
        "name": "total!: i64",
        "type_info": "Int8"
      },
      {
        "ordinal": 1,
        "name": "within_1h!: i64",
        "type_info": "Int8"
      },
      {
        "ordinal": 2,
        "name": "within_4h!: i64",
        "type_info": "Int8"
      },
      {
        "ordinal": 3,
        "name": "within_12h!: i64",
        "type_info": "Int8"
      },
      {
        "ordinal": 4,
        "name": "within_24h!: i64",
        "type_info": "Int8"
      },
      {
        "ordinal": 5,
        "name": "within_72h!: i64",
        "type_info": "Int8"
      }
    ],
    "parameters": {
      "Left": [
        "Int8",
        "Int8",
        "Int8",
        "Int8",
        "Int8",
        "Bytea"
      ]
    },
    "nullable": [
      null,
      null,
      null,
      null,
      null,
      null
    ]
  },
  "hash": "12b8d83d07a880862c8e2eac3ca989a3b263639379fc245ba13344e140944598"
}
